{"kind": "Listing", "data": {"modhash": "", "dist": 12, "children": [{"kind": "t3", "data": {"approved_at_utc": null, "subreddit": "javascript", "selftext": "Did you find or create something cool this week in javascript? \n\nShow us here!", "author_fullname": "t2_6l4z3", "saved": false, "mod_reason_title": null, "gilded": 0, "clicked": false, "title": "Showoff Saturday (October 31, 2020)", "link_flair_richtext": [], "subreddit_name_prefixed": "r/javascript", "hidden": false, "pwls": 6, "link_flair_css_class": "showoff", "downs": 0, "top_awarded_type": null, "hide_score": false, "name": "t3_jlh1ld", "quarantine": false, "link_flair_text_color": "dark", "upvote_ratio": 0.79, "author_flair_background_color": null, "subreddit_type": "public", "ups": 9, "total_awards_received": 0, "media_embed": {}, "author_flair_template_id": null, "is_original_content": false, "user_reports": [], "secure_media": null, "is_reddit_media_domain": false, "is_meta": false, "category": null, "secure_media_embed": {}, "link_flair_text": "Showoff Saturday", "can_mod_post": false, "score": 9, "approved_by": null, "author_premium": true, "thumbnail": "", "edited": false, "author_flair_css_class": null, "author_flair_richtext": [], "gildings": {}, "content_categories": null, "is_self": true, "mod_note": null, "created": 1604173689.0, "link_flair_type": "text", "wls": 6, "removed_by_category": null, "banned_by": null, "author_flair_type": "text", "domain": "self.javascript", "allow_live_comments": false, "selftext_html": "&lt;!-- SC_OFF --&gt;&lt;div class=\"md\"&gt;&lt;p&gt;Did you find or create something cool this week in javascript? &lt;/p&gt;\n\n&lt;p&gt;Show us here!&lt;/p&gt;\n&lt;/div&gt;&lt;!-- SC_ON --&gt;", "likes": null, "suggested_sort": null, "banned_at_utc": null, "view_count": null, "archived": false, "no_follow": true, "is_crosspostable": false, "pinned": false, "over_18": false, "all_awardings": [], "awarders": [], "media_only": false, "can_gild": false, "spoiler": false, "locked": false, "author_flair_text": null, "treatment_tags": [], "visited": false, "removed_by": null, "num_reports": null, "distinguished": "moderator", "subreddit_id": "t5_2qh30", "mod_reason_by": null, "removal_reason": null, "link_flair_background_color": "", "id": "jlh1ld", "is_robot_indexable": true, "report_reasons": null, "author": "AutoModerator", "discussion_type": null, "num_comments": 3, "send_replies": false, "whitelist_status": "all_ads", "contest_mode": false, "mod_reports": [], "author_patreon_flair": false, "author_flair_text_color": null, "permalink": "/r/javascript/comments/jlh1ld/showoff_saturday_october_31_2020/", "parent_whitelist_status": "all_ads", "stickied": true, "url": "https://www.reddit.com/r/javascript/comments/jlh1ld/showoff_saturday_october_31_2020/", "subreddit_subscribers": 1223522, "created_utc": 1604144889.0, "num_crossposts": 0, "media": null, "is_video": false}}, {"kind": "t3", "data": {"approved_at_utc": null, "subreddit": "javascript", "selftext": "**Monday, October 26 - Sunday, November 01**\n\n###Top Posts\n\n| score | comments | title &amp; link |\n|--|--|--|\n| 236  | [21 comments](/r/javascript/comments/jm2nuy/now_you_can_walk_inside_it_halflife_inspired_3d/) | [Now You Can Walk Inside It: Half-Life Inspired 3D Level with WebGL - Supports Touch Devices](https://oguzeroglu.github.io/ROYGBIV/demo/villeneuvedascq2/application.html)|\n| 231  | [30 comments](https://www.reddit.com/r/javascript/comments/jk6082/why_npm_lockfiles_can_be_a_security_blindspot_for/) | [Why npm lockfiles can be a security blindspot for injecting malicious modules](https://snyk.io/blog/why-npm-lockfiles-can-be-a-security-blindspot-for-injecting-malicious-modules/)|\n| 189  | [13 comments](https://www.reddit.com/r/javascript/comments/jigyqq/cypress_is_an_amazing_testing_framework_but_i/) | [Cypress is an amazing testing framework but I always thought it should be easier to write test setups, so I made cypress-routines](https://maxschmitt.me/posts/cypress-routines/)|\n| 188  | [6 comments](https://www.reddit.com/r/javascript/comments/jjpoqf/simplest_js_paint/) | [Simplest JS paint](https://hinty.io/devforth/simplest-js-paint/)|\n| 183  | [24 comments](/r/javascript/comments/jkw3pc/how_to_install_multiple_versions_of_the_same/) | [How to Install Multiple Versions of the Same Package in NPM &amp;#40;Handy tip!&amp;#41;](https://medium.com/weekly-webtips/how-to-install-multiple-versions-of-the-same-package-in-npm-71c29b12e253?source=friends_link&amp;sk=312eb0068aa2c375b7518e75fb901486)|\n| 168  | [8 comments](/r/javascript/comments/jlov8g/javaspooky_using_javascript_to_revive_an_old/) | [JavaSpooky: Using JavaScript to revive an old horror webcomic from a flashplayer grave.](https://dev.to/nickgottschlich/javaspooky-using-javascript-to-revive-an-old-horror-webcomic-from-a-flashplayer-grave-4dgb)|\n| 163  | [36 comments](https://www.reddit.com/r/javascript/comments/jj10k9/vanillatodo_a_case_study_on_viable_techniques_for/) | [Vanilla-todo: A case study on viable techniques for vanilla web development](https://github.com/morris/vanilla-todo)|\n| 132  | [19 comments](https://www.reddit.com/r/javascript/comments/jj1rt4/layout_projection_a_method_for_animating_browser/) | [Layout projection: A method for animating browser layouts at 60fps](https://mattperry.is/writing-code/layout-projection-animate-browser-layout-60fps)|\n| 113  | [21 comments](https://www.reddit.com/r/javascript/comments/jjfrte/what_a_yarn_workspace_is_and_the_problem_it_solves/) | [What A Yarn Workspace Is, And The Problem It Solves](https://planflow.dev/blog/what-is-a-yarn-workspace)|\n| 106  | [4 comments](https://www.reddit.com/r/javascript/comments/jj45eq/nextjs_10_automatic_image_optimisation_and_more/) | [Next.js 10 - automatic Image optimisation and more](https://github.com/vercel/next.js/releases/tag/v10.0.0)|\n\n\n\n\n&amp;nbsp;\n\n###Most Commented Posts\n\n| score | comments | title &amp; link |\n|--|--|--|\n| 2  | [33 comments](/r/javascript/comments/jlufex/askjs_whats_after_react/) | `[AskJS]` &amp;#91;AskJS&amp;#93; What's after React?|\n| 12  | [24 comments](https://www.reddit.com/r/javascript/comments/jit9xn/askjs_entry_level_js_interview/) | `[AskJS]` &amp;#91;AskJS&amp;#93; Entry Level JS Interview|\n| 92  | [20 comments](https://www.reddit.com/r/javascript/comments/jk1c01/free_and_unlimited_image_video_conversion/) | [Free and Unlimited Image &amp;amp; Video Conversion ENTIRELY in browser using FFMPEG compiled to WebAssembly. No Uploads! No backend!](https://fileconverter.digital)|\n| 0  | [19 comments](https://www.reddit.com/r/javascript/comments/jkhrsh/standardjs_1600_released/) | [StandardJS 16.0.0 Released](https://standardjs.com/changelog.html#1600---2020-10-28)|\n| 0  | [18 comments](https://www.reddit.com/r/javascript/comments/jj39m2/welcome_deno_does_this_mean_goodbye_to_nodejs/) | [Welcome Deno! Does this mean goodbye to Node.js?](https://www.stackbuilders.com/news/welcome-deno-does-this-mean-goodbye-to-node-js)|\n\n\n\n\n&amp;nbsp;\n\n###Top Ask JS\n\n| score | comments | title &amp; link |\n|--|--|--|\n| 4  | [17 comments](/r/javascript/comments/jlyt3m/askjs_should_i_compile_to_webassembly/) | `[AskJS]` &amp;#91;AskJS&amp;#93; Should I compile to WebAssembly?|\n| 0  | [4 comments](https://www.reddit.com/r/javascript/comments/jj3d42/askjs_nextjsreact_or_nuxtjsvue_for_an_headless/) | `[AskJS]` &amp;#91;AskJS&amp;#93; NextJS&amp;#40;React&amp;#41; or NuxtJS&amp;#40;Vue&amp;#41; for an Headless Shopify project?|\n| 0  | [0 comments](https://www.reddit.com/r/javascript/comments/jjxz0q/askjs_are_there_any_plans_to_create_dedicated/) | `[AskJS]` &amp;#91;AskJS&amp;#93; Are there any plans to create dedicated number plus operator and a dedicated string concatenation operator?|\n\n\n\n\n&amp;nbsp;\n\n###Top Showoffs\n\n| score  |  comment  |\n|--|--|\n| 2  |  /u/stardust-kid said [Applied for the job, got test assignment to make to-do list. Didn\u2019t like it and made to-do list of to-do lists instead.  https://structure.ninja doesn\u2019t support mobile yet, visit from desktop.   https...](/r/javascript/comments/jlh1ld/showoff_saturday_october_31_2020/gaqhkrz/?context=5) |\n| 2  |  /u/irekrog said [I made a mobile app for Android &amp;#40;in React Native&amp;#41; to store links and preview them. Links can be saved from external apps &amp;#40;like Chrome, Reddit etc&amp;#41;, from text input typing URL or from s...](/r/javascript/comments/jlh1ld/showoff_saturday_october_31_2020/gaovyi0/?context=5) |\n| 1  |  /u/lonaExe said [ Hey there, Im Jes.  I   made Shakespeare, a Firefox extension. Well to keep it simple, here's a   situation. You're in a formal online group or thread, and there is  this  one person annoying the hel...](/r/javascript/comments/jlh1ld/showoff_saturday_october_31_2020/gatfkng/?context=5) |\n\n\n\n\n&amp;nbsp;\n\n###Top Comments\n\n| score  |  comment  |\n|--|--|\n| 107  |  /u/Romanmir said [I presume it uses \u201cmiddle out\u201d compression?](/r/javascript/comments/jlhlvz/released_a_javascript_sdk_to_reduce_video/gap7sl4/?context=5) |\n| 69  |  /u/Cyberlane said [To;Dr;  npm i &lt;package_name_alias&gt;@npm:&lt;package_name&gt;](/r/javascript/comments/jkw3pc/how_to_install_multiple_versions_of_the_same/galszfj/?context=5) |\n| 65  |  /u/license-bot said [Thanks for sharing your open source project, but it looks like you haven't specified a license.  &gt; When you make a creative work &amp;#40;which includes code&amp;#41;, the work is under exclusive copyright by...](/r/javascript/comments/jlhlvz/released_a_javascript_sdk_to_reduce_video/gaoz0a5/?context=5) |\n| 61  |  /u/robotmayo said [Hell will freeze over before I work on an application that uses hard-coded html strings again.](/r/javascript/comments/jj10k9/vanillatodo_a_case_study_on_viable_techniques_for/gaa33gk/?context=5) |\n| 42  |  /u/babanbosama said [&gt; replace our ***aging*** bundling infrastructure with a new bundler  Deno is ... 2 years old?](/r/javascript/comments/jjk5x2/deno_15_release_notes/gad4o5y/?context=5) |\n\n\n\n\n&amp;nbsp;", "author_fullname": "t2_ydo5x7u", "saved": false, "mod_reason_title": null, "gilded": 0, "clicked": false, "title": "Your /r/javascript recap for the week of October 26 - November 01", "link_flair_richtext": [], "subreddit_name_prefixed": "r/javascript", "hidden": false, "pwls": 6, "link_flair_css_class": null, "downs": 0, "top_awarded_type": null, "hide_score": false, "name": "t3_jml5ae", "quarantine": false, "link_flair_text_color": "dark", "upvote_ratio": 1.0, "author_flair_background_color": null, "subreddit_type": "public", "ups": 4, "total_awards_received": 0, "media_embed": {}, "author_flair_template_id": null, "is_original_content": false, "user_reports": [], "secure_media": null, "is_reddit_media_domain": false, "is_meta": false, "category": null, "secure_media_embed": {}, "link_flair_text": "Subreddit Stats", "can_mod_post": false, "score": 4, "approved_by": null, "author_premium": false, "thumbnail": "", "edited": false, "author_flair_css_class": null, "author_flair_richtext": [], "gildings": {}, "content_categories": null, "is_self": true, "mod_note": null, "created": 1604341914.0, "link_flair_type": "text", "wls": 6, "removed_by_category": null, "banned_by": null, "author_flair_type": "text", "domain": "self.javascript", "allow_live_comments": false, "selftext_html": "&lt;!-- SC_OFF --&gt;&lt;div class=\"md\"&gt;&lt;p&gt;&lt;strong&gt;Monday, October 26 - Sunday, November 01&lt;/strong&gt;&lt;/p&gt;\n\n&lt;h3&gt;Top Posts&lt;/h3&gt;\n\n&lt;table&gt;&lt;thead&gt;\n&lt;tr&gt;\n&lt;th&gt;score&lt;/th&gt;\n&lt;th&gt;comments&lt;/th&gt;\n&lt;th&gt;title &amp;amp; link&lt;/th&gt;\n&lt;/tr&gt;\n&lt;/thead&gt;&lt;tbody&gt;\n&lt;tr&gt;\n&lt;td&gt;236&lt;/td&gt;\n&lt;td&gt;&lt;a href=\"/r/javascript/comments/jm2nuy/now_you_can_walk_inside_it_halflife_inspired_3d/\"&gt;21 comments&lt;/a&gt;&lt;/td&gt;\n&lt;td&gt;&lt;a href=\"https://oguzeroglu.github.io/ROYGBIV/demo/villeneuvedascq2/application.html\"&gt;Now You Can Walk Inside It: Half-Life Inspired 3D Level with WebGL - Supports Touch Devices&lt;/a&gt;&lt;/td&gt;\n&lt;/tr&gt;\n&lt;tr&gt;\n&lt;td&gt;231&lt;/td&gt;\n&lt;td&gt;&lt;a href=\"https://www.reddit.com/r/javascript/comments/jk6082/why_npm_lockfiles_can_be_a_security_blindspot_for/\"&gt;30 comments&lt;/a&gt;&lt;/td&gt;\n&lt;td&gt;&lt;a href=\"https://snyk.io/blog/why-npm-lockfiles-can-be-a-security-blindspot-for-injecting-malicious-modules/\"&gt;Why npm lockfiles can be a security blindspot for injecting malicious modules&lt;/a&gt;&lt;/td&gt;\n&lt;/tr&gt;\n&lt;tr&gt;\n&lt;td&gt;189&lt;/td&gt;\n&lt;td&gt;&lt;a href=\"https://www.reddit.com/r/javascript/comments/jigyqq/cypress_is_an_amazing_testing_framework_but_i/\"&gt;13 comments&lt;/a&gt;&lt;/td&gt;\n&lt;td&gt;&lt;a href=\"https://maxschmitt.me/posts/cypress-routines/\"&gt;Cypress is an amazing testing framework but I always thought it should be easier to write test setups, so I made cypress-routines&lt;/a&gt;&lt;/td&gt;\n&lt;/tr&gt;\n&lt;tr&gt;\n&lt;td&gt;188&lt;/td&gt;\n&lt;td&gt;&lt;a href=\"https://www.reddit.com/r/javascript/comments/jjpoqf/simplest_js_paint/\"&gt;6 comments&lt;/a&gt;&lt;/td&gt;\n&lt;td&gt;&lt;a href=\"https://hinty.io/devforth/simplest-js-paint/\"&gt;Simplest JS paint&lt;/a&gt;&lt;/td&gt;\n&lt;/tr&gt;\n&lt;tr&gt;\n&lt;td&gt;183&lt;/td&gt;\n&lt;td&gt;&lt;a href=\"/r/javascript/comments/jkw3pc/how_to_install_multiple_versions_of_the_same/\"&gt;24 comments&lt;/a&gt;&lt;/td&gt;\n&lt;td&gt;&lt;a href=\"https://medium.com/weekly-webtips/how-to-install-multiple-versions-of-the-same-package-in-npm-71c29b12e253?source=friends_link&amp;amp;sk=312eb0068aa2c375b7518e75fb901486\"&gt;How to Install Multiple Versions of the Same Package in NPM &amp;#40;Handy tip!&amp;#41;&lt;/a&gt;&lt;/td&gt;\n&lt;/tr&gt;\n&lt;tr&gt;\n&lt;td&gt;168&lt;/td&gt;\n&lt;td&gt;&lt;a href=\"/r/javascript/comments/jlov8g/javaspooky_using_javascript_to_revive_an_old/\"&gt;8 comments&lt;/a&gt;&lt;/td&gt;\n&lt;td&gt;&lt;a href=\"https://dev.to/nickgottschlich/javaspooky-using-javascript-to-revive-an-old-horror-webcomic-from-a-flashplayer-grave-4dgb\"&gt;JavaSpooky: Using JavaScript to revive an old horror webcomic from a flashplayer grave.&lt;/a&gt;&lt;/td&gt;\n&lt;/tr&gt;\n&lt;tr&gt;\n&lt;td&gt;163&lt;/td&gt;\n&lt;td&gt;&lt;a href=\"https://www.reddit.com/r/javascript/comments/jj10k9/vanillatodo_a_case_study_on_viable_techniques_for/\"&gt;36 comments&lt;/a&gt;&lt;/td&gt;\n&lt;td&gt;&lt;a href=\"https://github.com/morris/vanilla-todo\"&gt;Vanilla-todo: A case study on viable techniques for vanilla web development&lt;/a&gt;&lt;/td&gt;\n&lt;/tr&gt;\n&lt;tr&gt;\n&lt;td&gt;132&lt;/td&gt;\n&lt;td&gt;&lt;a href=\"https://www.reddit.com/r/javascript/comments/jj1rt4/layout_projection_a_method_for_animating_browser/\"&gt;19 comments&lt;/a&gt;&lt;/td&gt;\n&lt;td&gt;&lt;a href=\"https://mattperry.is/writing-code/layout-projection-animate-browser-layout-60fps\"&gt;Layout projection: A method for animating browser layouts at 60fps&lt;/a&gt;&lt;/td&gt;\n&lt;/tr&gt;\n&lt;tr&gt;\n&lt;td&gt;113&lt;/td&gt;\n&lt;td&gt;&lt;a href=\"https://www.reddit.com/r/javascript/comments/jjfrte/what_a_yarn_workspace_is_and_the_problem_it_solves/\"&gt;21 comments&lt;/a&gt;&lt;/td&gt;\n&lt;td&gt;&lt;a href=\"https://planflow.dev/blog/what-is-a-yarn-workspace\"&gt;What A Yarn Workspace Is, And The Problem It Solves&lt;/a&gt;&lt;/td&gt;\n&lt;/tr&gt;\n&lt;tr&gt;\n&lt;td&gt;106&lt;/td&gt;\n&lt;td&gt;&lt;a href=\"https://www.reddit.com/r/javascript/comments/jj45eq/nextjs_10_automatic_image_optimisation_and_more/\"&gt;4 comments&lt;/a&gt;&lt;/td&gt;\n&lt;td&gt;&lt;a href=\"https://github.com/vercel/next.js/releases/tag/v10.0.0\"&gt;Next.js 10 - automatic Image optimisation and more&lt;/a&gt;&lt;/td&gt;\n&lt;/tr&gt;\n&lt;/tbody&gt;&lt;/table&gt;\n\n&lt;p&gt;&amp;nbsp;&lt;/p&gt;\n\n&lt;h3&gt;Most Commented Posts&lt;/h3&gt;\n\n&lt;table&gt;&lt;thead&gt;\n&lt;tr&gt;\n&lt;th&gt;score&lt;/th&gt;\n&lt;th&gt;comments&lt;/th&gt;\n&lt;th&gt;title &amp;amp; link&lt;/th&gt;\n&lt;/tr&gt;\n&lt;/thead&gt;&lt;tbody&gt;\n&lt;tr&gt;\n&lt;td&gt;2&lt;/td&gt;\n&lt;td&gt;&lt;a href=\"/r/javascript/comments/jlufex/askjs_whats_after_react/\"&gt;33 comments&lt;/a&gt;&lt;/td&gt;\n&lt;td&gt;&lt;code&gt;[AskJS]&lt;/code&gt; &amp;#91;AskJS&amp;#93; What&amp;#39;s after React?&lt;/td&gt;\n&lt;/tr&gt;\n&lt;tr&gt;\n&lt;td&gt;12&lt;/td&gt;\n&lt;td&gt;&lt;a href=\"https://www.reddit.com/r/javascript/comments/jit9xn/askjs_entry_level_js_interview/\"&gt;24 comments&lt;/a&gt;&lt;/td&gt;\n&lt;td&gt;&lt;code&gt;[AskJS]&lt;/code&gt; &amp;#91;AskJS&amp;#93; Entry Level JS Interview&lt;/td&gt;\n&lt;/tr&gt;\n&lt;tr&gt;\n&lt;td&gt;92&lt;/td&gt;\n&lt;td&gt;&lt;a href=\"https://www.reddit.com/r/javascript/comments/jk1c01/free_and_unlimited_image_video_conversion/\"&gt;20 comments&lt;/a&gt;&lt;/td&gt;\n&lt;td&gt;&lt;a href=\"https://fileconverter.digital\"&gt;Free and Unlimited Image &amp;amp; Video Conversion ENTIRELY in browser using FFMPEG compiled to WebAssembly. No Uploads! No backend!&lt;/a&gt;&lt;/td&gt;\n&lt;/tr&gt;\n&lt;tr&gt;\n&lt;td&gt;0&lt;/td&gt;\n&lt;td&gt;&lt;a href=\"https://www.reddit.com/r/javascript/comments/jkhrsh/standardjs_1600_released/\"&gt;19 comments&lt;/a&gt;&lt;/td&gt;\n&lt;td&gt;&lt;a href=\"https://standardjs.com/changelog.html#1600---2020-10-28\"&gt;StandardJS 16.0.0 Released&lt;/a&gt;&lt;/td&gt;\n&lt;/tr&gt;\n&lt;tr&gt;\n&lt;td&gt;0&lt;/td&gt;\n&lt;td&gt;&lt;a href=\"https://www.reddit.com/r/javascript/comments/jj39m2/welcome_deno_does_this_mean_goodbye_to_nodejs/\"&gt;18 comments&lt;/a&gt;&lt;/td&gt;\n&lt;td&gt;&lt;a href=\"https://www.stackbuilders.com/news/welcome-deno-does-this-mean-goodbye-to-node-js\"&gt;Welcome Deno! Does this mean goodbye to Node.js?&lt;/a&gt;&lt;/td&gt;\n&lt;/tr&gt;\n&lt;/tbody&gt;&lt;/table&gt;\n\n&lt;p&gt;&amp;nbsp;&lt;/p&gt;\n\n&lt;h3&gt;Top Ask JS&lt;/h3&gt;\n\n&lt;table&gt;&lt;thead&gt;\n&lt;tr&gt;\n&lt;th&gt;score&lt;/th&gt;\n&lt;th&gt;comments&lt;/th&gt;\n&lt;th&gt;title &amp;amp; link&lt;/th&gt;\n&lt;/tr&gt;\n&lt;/thead&gt;&lt;tbody&gt;\n&lt;tr&gt;\n&lt;td&gt;4&lt;/td&gt;\n&lt;td&gt;&lt;a href=\"/r/javascript/comments/jlyt3m/askjs_should_i_compile_to_webassembly/\"&gt;17 comments&lt;/a&gt;&lt;/td&gt;\n&lt;td&gt;&lt;code&gt;[AskJS]&lt;/code&gt; &amp;#91;AskJS&amp;#93; Should I compile to WebAssembly?&lt;/td&gt;\n&lt;/tr&gt;\n&lt;tr&gt;\n&lt;td&gt;0&lt;/td&gt;\n&lt;td&gt;&lt;a href=\"https://www.reddit.com/r/javascript/comments/jj3d42/askjs_nextjsreact_or_nuxtjsvue_for_an_headless/\"&gt;4 comments&lt;/a&gt;&lt;/td&gt;\n&lt;td&gt;&lt;code&gt;[AskJS]&lt;/code&gt; &amp;#91;AskJS&amp;#93; NextJS&amp;#40;React&amp;#41; or NuxtJS&amp;#40;Vue&amp;#41; for an Headless Shopify project?&lt;/td&gt;\n&lt;/tr&gt;\n&lt;tr&gt;\n&lt;td&gt;0&lt;/td&gt;\n&lt;td&gt;&lt;a href=\"https://www.reddit.com/r/javascript/comments/jjxz0q/askjs_are_there_any_plans_to_create_dedicated/\"&gt;0 comments&lt;/a&gt;&lt;/td&gt;\n&lt;td&gt;&lt;code&gt;[AskJS]&lt;/code&gt; &amp;#91;AskJS&amp;#93; Are there any plans to create dedicated number plus operator and a dedicated string concatenation operator?&lt;/td&gt;\n&lt;/tr&gt;\n&lt;/tbody&gt;&lt;/table&gt;\n\n&lt;p&gt;&amp;nbsp;&lt;/p&gt;\n\n&lt;h3&gt;Top Showoffs&lt;/h3&gt;\n\n&lt;table&gt;&lt;thead&gt;\n&lt;tr&gt;\n&lt;th&gt;score&lt;/th&gt;\n&lt;th&gt;comment&lt;/th&gt;\n&lt;/tr&gt;\n&lt;/thead&gt;&lt;tbody&gt;\n&lt;tr&gt;\n&lt;td&gt;2&lt;/td&gt;\n&lt;td&gt;&lt;a href=\"/u/stardust-kid\"&gt;/u/stardust-kid&lt;/a&gt; said &lt;a href=\"/r/javascript/comments/jlh1ld/showoff_saturday_october_31_2020/gaqhkrz/?context=5\"&gt;Applied for the job, got test assignment to make to-do list. Didn\u2019t like it and made to-do list of to-do lists instead.  https://structure.ninja doesn\u2019t support mobile yet, visit from desktop.   https...&lt;/a&gt;&lt;/td&gt;\n&lt;/tr&gt;\n&lt;tr&gt;\n&lt;td&gt;2&lt;/td&gt;\n&lt;td&gt;&lt;a href=\"/u/irekrog\"&gt;/u/irekrog&lt;/a&gt; said &lt;a href=\"/r/javascript/comments/jlh1ld/showoff_saturday_october_31_2020/gaovyi0/?context=5\"&gt;I made a mobile app for Android &amp;#40;in React Native&amp;#41; to store links and preview them. Links can be saved from external apps &amp;#40;like Chrome, Reddit etc&amp;#41;, from text input typing URL or from s...&lt;/a&gt;&lt;/td&gt;\n&lt;/tr&gt;\n&lt;tr&gt;\n&lt;td&gt;1&lt;/td&gt;\n&lt;td&gt;&lt;a href=\"/u/lonaExe\"&gt;/u/lonaExe&lt;/a&gt; said &lt;a href=\"/r/javascript/comments/jlh1ld/showoff_saturday_october_31_2020/gatfkng/?context=5\"&gt; Hey there, Im Jes.  I   made Shakespeare, a Firefox extension. Well to keep it simple, here&amp;#39;s a   situation. You&amp;#39;re in a formal online group or thread, and there is  this  one person annoying the hel...&lt;/a&gt;&lt;/td&gt;\n&lt;/tr&gt;\n&lt;/tbody&gt;&lt;/table&gt;\n\n&lt;p&gt;&amp;nbsp;&lt;/p&gt;\n\n&lt;h3&gt;Top Comments&lt;/h3&gt;\n\n&lt;table&gt;&lt;thead&gt;\n&lt;tr&gt;\n&lt;th&gt;score&lt;/th&gt;\n&lt;th&gt;comment&lt;/th&gt;\n&lt;/tr&gt;\n&lt;/thead&gt;&lt;tbody&gt;\n&lt;tr&gt;\n&lt;td&gt;107&lt;/td&gt;\n&lt;td&gt;&lt;a href=\"/u/Romanmir\"&gt;/u/Romanmir&lt;/a&gt; said &lt;a href=\"/r/javascript/comments/jlhlvz/released_a_javascript_sdk_to_reduce_video/gap7sl4/?context=5\"&gt;I presume it uses \u201cmiddle out\u201d compression?&lt;/a&gt;&lt;/td&gt;\n&lt;/tr&gt;\n&lt;tr&gt;\n&lt;td&gt;69&lt;/td&gt;\n&lt;td&gt;&lt;a href=\"/u/Cyberlane\"&gt;/u/Cyberlane&lt;/a&gt; said &lt;a href=\"/r/javascript/comments/jkw3pc/how_to_install_multiple_versions_of_the_same/galszfj/?context=5\"&gt;To;Dr;  npm i &amp;lt;package_name_alias&amp;gt;@npm:&amp;lt;package_name&amp;gt;&lt;/a&gt;&lt;/td&gt;\n&lt;/tr&gt;\n&lt;tr&gt;\n&lt;td&gt;65&lt;/td&gt;\n&lt;td&gt;&lt;a href=\"/u/license-bot\"&gt;/u/license-bot&lt;/a&gt; said &lt;a href=\"/r/javascript/comments/jlhlvz/released_a_javascript_sdk_to_reduce_video/gaoz0a5/?context=5\"&gt;Thanks for sharing your open source project, but it looks like you haven&amp;#39;t specified a license.  &amp;gt; When you make a creative work &amp;#40;which includes code&amp;#41;, the work is under exclusive copyright by...&lt;/a&gt;&lt;/td&gt;\n&lt;/tr&gt;\n&lt;tr&gt;\n&lt;td&gt;61&lt;/td&gt;\n&lt;td&gt;&lt;a href=\"/u/robotmayo\"&gt;/u/robotmayo&lt;/a&gt; said &lt;a href=\"/r/javascript/comments/jj10k9/vanillatodo_a_case_study_on_viable_techniques_for/gaa33gk/?context=5\"&gt;Hell will freeze over before I work on an application that uses hard-coded html strings again.&lt;/a&gt;&lt;/td&gt;\n&lt;/tr&gt;\n&lt;tr&gt;\n&lt;td&gt;42&lt;/td&gt;\n&lt;td&gt;&lt;a href=\"/u/babanbosama\"&gt;/u/babanbosama&lt;/a&gt; said &lt;a href=\"/r/javascript/comments/jjk5x2/deno_15_release_notes/gad4o5y/?context=5\"&gt;&amp;gt; replace our &lt;strong&gt;&lt;em&gt;aging&lt;/em&gt;&lt;/strong&gt; bundling infrastructure with a new bundler  Deno is ... 2 years old?&lt;/a&gt;&lt;/td&gt;\n&lt;/tr&gt;\n&lt;/tbody&gt;&lt;/table&gt;\n\n&lt;p&gt;&amp;nbsp;&lt;/p&gt;\n&lt;/div&gt;&lt;!-- SC_ON --&gt;", "likes": null, "suggested_sort": null, "banned_at_utc": null, "view_count": null, "archived": false, "no_follow": false, "is_crosspostable": false, "pinned": false, "over_18": false, "all_awardings": [], "awarders": [], "media_only": false, "can_gild": false, "spoiler": false, "locked": false, "author_flair_text": null, "treatment_tags": [], "visited": false, "removed_by": null, "num_reports": null, "distinguished": null, "subreddit_id": "t5_2qh30", "mod_reason_by": null, "removal_reason": null, "link_flair_background_color": "", "id": "jml5ae", "is_robot_indexable": true, "report_reasons": null, "author": "subredditsummarybot", "discussion_type": null, "num_comments": 1, "send_replies": true, "whitelist_status": "all_ads", "contest_mode": false, "mod_reports": [], "author_patreon_flair": false, "author_flair_text_color": null, "permalink": "/r/javascript/comments/jml5ae/your_rjavascript_recap_for_the_week_of_october_26/", "parent_whitelist_status": "all_ads", "stickied": true, "url": "https://www.reddit.com/r/javascript/comments/jml5ae/your_rjavascript_recap_for_the_week_of_october_26/", "subreddit_subscribers": 1223522, "created_utc": 1604313114.0, "num_crossposts": 0, "media": null, "is_video": false}}, {"kind": "t3", "data": {"approved_at_utc": null, "subreddit": "javascript", "selftext": "", "author_fullname": "t2_rtj6x", "saved": false, "mod_reason_title": null, "gilded": 0, "clicked": false, "title": "Open source file uploader Uppy adds support for Unsplash", "link_flair_richtext": [], "subreddit_name_prefixed": "r/javascript", "hidden": false, "pwls": 6, "link_flair_css_class": null, "downs": 0, "top_awarded_type": null, "hide_score": true, "name": "t3_jn9765", "quarantine": false, "link_flair_text_color": "dark", "upvote_ratio": 0.92, "author_flair_background_color": null, "subreddit_type": "public", "ups": 10, "total_awards_received": 0, "media_embed": {}, "author_flair_template_id": null, "is_original_content": false, "user_reports": [], "secure_media": null, "is_reddit_media_domain": false, "is_meta": false, "category": null, "secure_media_embed": {}, "link_flair_text": null, "can_mod_post": false, "score": 10, "approved_by": null, "author_premium": false, "thumbnail": "", "edited": false, "author_flair_css_class": null, "author_flair_richtext": [], "gildings": {}, "content_categories": null, "is_self": false, "mod_note": null, "created": 1604434318.0, "link_flair_type": "text", "wls": 6, "removed_by_category": null, "banned_by": null, "author_flair_type": "text", "domain": "uppy.io", "allow_live_comments": true, "selftext_html": null, "likes": null, "suggested_sort": null, "banned_at_utc": null, "url_overridden_by_dest": "https://uppy.io/blog/2020/10/1.22/", "view_count": null, "archived": false, "no_follow": false, "is_crosspostable": false, "pinned": false, "over_18": false, "all_awardings": [], "awarders": [], "media_only": false, "can_gild": false, "spoiler": false, "locked": false, "author_flair_text": null, "treatment_tags": [], "visited": false, "removed_by": null, "num_reports": null, "distinguished": null, "subreddit_id": "t5_2qh30", "mod_reason_by": null, "removal_reason": null, "link_flair_background_color": "", "id": "jn9765", "is_robot_indexable": true, "report_reasons": null, "author": "kevinvz", "discussion_type": null, "num_comments": 0, "send_replies": true, "whitelist_status": "all_ads", "contest_mode": false, "mod_reports": [], "author_patreon_flair": false, "author_flair_text_color": null, "permalink": "/r/javascript/comments/jn9765/open_source_file_uploader_uppy_adds_support_for/", "parent_whitelist_status": "all_ads", "stickied": false, "url": "https://uppy.io/blog/2020/10/1.22/", "subreddit_subscribers": 1223522, "created_utc": 1604405518.0, "num_crossposts": 0, "media": null, "is_video": false}}, {"kind": "t3", "data": {"approved_at_utc": null, "subreddit": "javascript", "selftext": "I'm a front end dev w/ mostly Vue experience and is looking to build my first mobile side project. I want to build something ASAP, and it seems that the easiest options were vue-native(which just compiles into RN) and *NativeScript*.\n\nFrom my limited research it seemed that from a tech stack perspective NativeScript seemed better than React Native since it can access native apis. And the main downside is the lack of big community like the one RN has. However, it seems that there's literally NOBODY using NativeScript.\n\nMost conversations on Reddit about NativeScript are at least 1 year old. And the NativeScript npm package install timeline also looks dead post mid 2019.\n\n**Why?** Vue's getting more popular, people are getting pissed at React Native, shouldn't NativeScript also grow with it?", "author_fullname": "t2_j2z0g", "saved": false, "mod_reason_title": null, "gilded": 0, "clicked": false, "title": "[AskJS] Why is NativeScript so dead?", "link_flair_richtext": [], "subreddit_name_prefixed": "r/javascript", "hidden": false, "pwls": 6, "link_flair_css_class": "AskJS", "downs": 0, "top_awarded_type": null, "hide_score": false, "name": "t3_jn7e5g", "quarantine": false, "link_flair_text_color": "dark", "upvote_ratio": 0.7, "author_flair_background_color": null, "subreddit_type": "public", "ups": 16, "total_awards_received": 0, "media_embed": {}, "author_flair_template_id": null, "is_original_content": false, "user_reports": [], "secure_media": null, "is_reddit_media_domain": false, "is_meta": false, "category": null, "secure_media_embed": {}, "link_flair_text": "AskJS", "can_mod_post": false, "score": 16, "approved_by": null, "author_premium": false, "thumbnail": "", "edited": false, "author_flair_css_class": null, "author_flair_richtext": [], "gildings": {}, "content_categories": null, "is_self": true, "mod_note": null, "created": 1604424547.0, "link_flair_type": "text", "wls": 6, "removed_by_category": null, "banned_by": null, "author_flair_type": "text", "domain": "self.javascript", "allow_live_comments": false, "selftext_html": "&lt;!-- SC_OFF --&gt;&lt;div class=\"md\"&gt;&lt;p&gt;I&amp;#39;m a front end dev w/ mostly Vue experience and is looking to build my first mobile side project. I want to build something ASAP, and it seems that the easiest options were vue-native(which just compiles into RN) and &lt;em&gt;NativeScript&lt;/em&gt;.&lt;/p&gt;\n\n&lt;p&gt;From my limited research it seemed that from a tech stack perspective NativeScript seemed better than React Native since it can access native apis. And the main downside is the lack of big community like the one RN has. However, it seems that there&amp;#39;s literally NOBODY using NativeScript.&lt;/p&gt;\n\n&lt;p&gt;Most conversations on Reddit about NativeScript are at least 1 year old. And the NativeScript npm package install timeline also looks dead post mid 2019.&lt;/p&gt;\n\n&lt;p&gt;&lt;strong&gt;Why?&lt;/strong&gt; Vue&amp;#39;s getting more popular, people are getting pissed at React Native, shouldn&amp;#39;t NativeScript also grow with it?&lt;/p&gt;\n&lt;/div&gt;&lt;!-- SC_ON --&gt;", "likes": null, "suggested_sort": null, "banned_at_utc": null, "view_count": null, "archived": false, "no_follow": false, "is_crosspostable": false, "pinned": false, "over_18": false, "all_awardings": [], "awarders": [], "media_only": false, "can_gild": false, "spoiler": false, "locked": false, "author_flair_text": null, "treatment_tags": [], "visited": false, "removed_by": null, "num_reports": null, "distinguished": null, "subreddit_id": "t5_2qh30", "mod_reason_by": null, "removal_reason": null, "link_flair_background_color": "", "id": "jn7e5g", "is_robot_indexable": true, "report_reasons": null, "author": "Chesil", "discussion_type": null, "num_comments": 12, "send_replies": true, "whitelist_status": "all_ads", "contest_mode": false, "mod_reports": [], "author_patreon_flair": false, "author_flair_text_color": null, "permalink": "/r/javascript/comments/jn7e5g/askjs_why_is_nativescript_so_dead/", "parent_whitelist_status": "all_ads", "stickied": false, "url": "https://www.reddit.com/r/javascript/comments/jn7e5g/askjs_why_is_nativescript_so_dead/", "subreddit_subscribers": 1223522, "created_utc": 1604395747.0, "num_crossposts": 0, "media": null, "is_video": false}}, {"kind": "t3", "data": {"approved_at_utc": null, "subreddit": "javascript", "selftext": "", "author_fullname": "t2_3bhyn", "saved": false, "mod_reason_title": null, "gilded": 0, "clicked": false, "title": "Supabase.js 1.0 - The open source Firebase alternative. Supabase adds realtime and restful APIs to Postgres without a single line of code", "link_flair_richtext": [], "subreddit_name_prefixed": "r/javascript", "hidden": false, "pwls": 6, "link_flair_css_class": null, "downs": 0, "top_awarded_type": null, "hide_score": false, "name": "t3_jmpmlm", "quarantine": false, "link_flair_text_color": "dark", "upvote_ratio": 0.98, "author_flair_background_color": null, "subreddit_type": "public", "ups": 365, "total_awards_received": 1, "media_embed": {}, "author_flair_template_id": null, "is_original_content": false, "user_reports": [], "secure_media": null, "is_reddit_media_domain": false, "is_meta": false, "category": null, "secure_media_embed": {}, "link_flair_text": null, "can_mod_post": false, "score": 365, "approved_by": null, "author_premium": true, "thumbnail": "", "edited": false, "author_flair_css_class": null, "author_flair_richtext": [], "gildings": {}, "content_categories": null, "is_self": false, "mod_note": null, "created": 1604360166.0, "link_flair_type": "text", "wls": 6, "removed_by_category": null, "banned_by": null, "author_flair_type": "text", "domain": "supabase.io", "allow_live_comments": false, "selftext_html": null, "likes": null, "suggested_sort": null, "banned_at_utc": null, "url_overridden_by_dest": "https://supabase.io/", "view_count": null, "archived": false, "no_follow": false, "is_crosspostable": false, "pinned": false, "over_18": false, "all_awardings": [{"giver_coin_reward": null, "subreddit_id": null, "is_new": false, "days_of_drip_extension": 0, "coin_price": 500, "id": "award_1f0462ee-18f5-4f33-89cf-f1f79336a452", "penny_donate": null, "award_sub_type": "GLOBAL", "coin_reward": 100, "icon_url": "https://i.redd.it/award_images/t5_22cerq/0o2j782f00e41_WholesomeSuperpro.png", "days_of_premium": 0, "tiers_by_required_awardings": null, "resized_icons": [{"url": "https://preview.redd.it/award_images/t5_22cerq/0o2j782f00e41_WholesomeSuperpro.png?width=16&amp;height=16&amp;auto=webp&amp;s=3ca7dc1f4e12ca386a561446e72f772d38ba49d8", "width": 16, "height": 16}, {"url": "https://preview.redd.it/award_images/t5_22cerq/0o2j782f00e41_WholesomeSuperpro.png?width=32&amp;height=32&amp;auto=webp&amp;s=c19d1e661e4aa6a9326a9f0b74b3ebf5d9f7a75e", "width": 32, "height": 32}, {"url": "https://preview.redd.it/award_images/t5_22cerq/0o2j782f00e41_WholesomeSuperpro.png?width=48&amp;height=48&amp;auto=webp&amp;s=ed063580825e72b0ae63fe30c807b453b1362694", "width": 48, "height": 48}, {"url": "https://preview.redd.it/award_images/t5_22cerq/0o2j782f00e41_WholesomeSuperpro.png?width=64&amp;height=64&amp;auto=webp&amp;s=7176b4b72b850e3e052138fe8b3967c4c5b52dae", "width": 64, "height": 64}, {"url": "https://preview.redd.it/award_images/t5_22cerq/0o2j782f00e41_WholesomeSuperpro.png?width=128&amp;height=128&amp;auto=webp&amp;s=f7b307840995777f9ae04699d019740658ba0e77", "width": 128, "height": 128}], "icon_width": 2048, "static_icon_width": 2048, "start_date": null, "is_enabled": true, "awardings_required_to_grant_benefits": null, "description": "When you come across a feel-good thing. Gives %{coin_symbol}100 Coins to both the author and the community.", "end_date": null, "subreddit_coin_reward": 100, "count": 1, "static_icon_height": 2048, "name": "Wholesome (Pro)", "resized_static_icons": [{"url": "https://preview.redd.it/award_images/t5_22cerq/0o2j782f00e41_WholesomeSuperpro.png?width=16&amp;height=16&amp;auto=webp&amp;s=3ca7dc1f4e12ca386a561446e72f772d38ba49d8", "width": 16, "height": 16}, {"url": "https://preview.redd.it/award_images/t5_22cerq/0o2j782f00e41_WholesomeSuperpro.png?width=32&amp;height=32&amp;auto=webp&amp;s=c19d1e661e4aa6a9326a9f0b74b3ebf5d9f7a75e", "width": 32, "height": 32}, {"url": "https://preview.redd.it/award_images/t5_22cerq/0o2j782f00e41_WholesomeSuperpro.png?width=48&amp;height=48&amp;auto=webp&amp;s=ed063580825e72b0ae63fe30c807b453b1362694", "width": 48, "height": 48}, {"url": "https://preview.redd.it/award_images/t5_22cerq/0o2j782f00e41_WholesomeSuperpro.png?width=64&amp;height=64&amp;auto=webp&amp;s=7176b4b72b850e3e052138fe8b3967c4c5b52dae", "width": 64, "height": 64}, {"url": "https://preview.redd.it/award_images/t5_22cerq/0o2j782f00e41_WholesomeSuperpro.png?width=128&amp;height=128&amp;auto=webp&amp;s=f7b307840995777f9ae04699d019740658ba0e77", "width": 128, "height": 128}], "icon_format": null, "icon_height": 2048, "penny_price": null, "award_type": "global", "static_icon_url": "https://i.redd.it/award_images/t5_22cerq/0o2j782f00e41_WholesomeSuperpro.png"}], "awarders": [], "media_only": false, "can_gild": false, "spoiler": false, "locked": false, "author_flair_text": null, "treatment_tags": [], "visited": false, "removed_by": null, "num_reports": null, "distinguished": null, "subreddit_id": "t5_2qh30", "mod_reason_by": null, "removal_reason": null, "link_flair_background_color": "", "id": "jmpmlm", "is_robot_indexable": true, "report_reasons": null, "author": "magenta_placenta", "discussion_type": null, "num_comments": 45, "send_replies": true, "whitelist_status": "all_ads", "contest_mode": false, "mod_reports": [], "author_patreon_flair": false, "author_flair_text_color": null, "permalink": "/r/javascript/comments/jmpmlm/supabasejs_10_the_open_source_firebase/", "parent_whitelist_status": "all_ads", "stickied": false, "url": "https://supabase.io/", "subreddit_subscribers": 1223522, "created_utc": 1604331366.0, "num_crossposts": 0, "media": null, "is_video": false}}, {"kind": "t3", "data": {"approved_at_utc": null, "subreddit": "javascript", "selftext": "", "author_fullname": "t2_op9pz", "saved": false, "mod_reason_title": null, "gilded": 0, "clicked": false, "title": "ts-audio v0.4.5 is out! :)", "link_flair_richtext": [], "subreddit_name_prefixed": "r/javascript", "hidden": false, "pwls": 6, "link_flair_css_class": null, "downs": 0, "top_awarded_type": null, "hide_score": true, "name": "t3_jn9h63", "quarantine": false, "link_flair_text_color": "dark", "upvote_ratio": 1.0, "author_flair_background_color": null, "subreddit_type": "public", "ups": 2, "total_awards_received": 0, "media_embed": {}, "author_flair_template_id": null, "is_original_content": false, "user_reports": [], "secure_media": null, "is_reddit_media_domain": false, "is_meta": false, "category": null, "secure_media_embed": {}, "link_flair_text": null, "can_mod_post": false, "score": 2, "approved_by": null, "author_premium": false, "thumbnail": "", "edited": false, "author_flair_css_class": null, "author_flair_richtext": [], "gildings": {}, "content_categories": null, "is_self": false, "mod_note": null, "created": 1604435627.0, "link_flair_type": "text", "wls": 6, "removed_by_category": null, "banned_by": null, "author_flair_type": "text", "domain": "github.com", "allow_live_comments": false, "selftext_html": null, "likes": null, "suggested_sort": null, "banned_at_utc": null, "url_overridden_by_dest": "https://github.com/EvandroLG/ts-audio/releases/tag/v0.4.5", "view_count": null, "archived": false, "no_follow": false, "is_crosspostable": false, "pinned": false, "over_18": false, "all_awardings": [], "awarders": [], "media_only": false, "can_gild": false, "spoiler": false, "locked": false, "author_flair_text": null, "treatment_tags": [], "visited": false, "removed_by": null, "num_reports": null, "distinguished": null, "subreddit_id": "t5_2qh30", "mod_reason_by": null, "removal_reason": null, "link_flair_background_color": "", "id": "jn9h63", "is_robot_indexable": true, "report_reasons": null, "author": "evandrolg", "discussion_type": null, "num_comments": 0, "send_replies": true, "whitelist_status": "all_ads", "contest_mode": false, "mod_reports": [], "author_patreon_flair": false, "author_flair_text_color": null, "permalink": "/r/javascript/comments/jn9h63/tsaudio_v045_is_out/", "parent_whitelist_status": "all_ads", "stickied": false, "url": "https://github.com/EvandroLG/ts-audio/releases/tag/v0.4.5", "subreddit_subscribers": 1223522, "created_utc": 1604406827.0, "num_crossposts": 0, "media": null, "is_video": false}}, {"kind": "t3", "data": {"approved_at_utc": null, "subreddit": "javascript", "selftext": "", "author_fullname": "t2_r612c", "saved": false, "mod_reason_title": null, "gilded": 0, "clicked": false, "title": "JavaScript's Memory Management Explained", "link_flair_richtext": [], "subreddit_name_prefixed": "r/javascript", "hidden": false, "pwls": 6, "link_flair_css_class": null, "downs": 0, "top_awarded_type": null, "hide_score": false, "name": "t3_jmwx33", "quarantine": false, "link_flair_text_color": "dark", "upvote_ratio": 0.93, "author_flair_background_color": null, "subreddit_type": "public", "ups": 28, "total_awards_received": 0, "media_embed": {}, "author_flair_template_id": null, "is_original_content": false, "user_reports": [], "secure_media": null, "is_reddit_media_domain": false, "is_meta": false, "category": null, "secure_media_embed": {}, "link_flair_text": null, "can_mod_post": false, "score": 28, "approved_by": null, "author_premium": false, "thumbnail": "", "edited": false, "author_flair_css_class": null, "author_flair_richtext": [], "gildings": {}, "content_categories": null, "is_self": false, "mod_note": null, "created": 1604382140.0, "link_flair_type": "text", "wls": 6, "removed_by_category": null, "banned_by": null, "author_flair_type": "text", "domain": "felixgerschau.com", "allow_live_comments": true, "selftext_html": null, "likes": null, "suggested_sort": null, "banned_at_utc": null, "url_overridden_by_dest": "https://felixgerschau.com/javascript-memory-management/?ck_subscriber_id=478674400", "view_count": null, "archived": false, "no_follow": false, "is_crosspostable": false, "pinned": false, "over_18": false, "all_awardings": [], "awarders": [], "media_only": false, "can_gild": false, "spoiler": false, "locked": false, "author_flair_text": null, "treatment_tags": [], "visited": false, "removed_by": null, "num_reports": null, "distinguished": null, "subreddit_id": "t5_2qh30", "mod_reason_by": null, "removal_reason": null, "link_flair_background_color": "", "id": "jmwx33", "is_robot_indexable": true, "report_reasons": null, "author": "shadowsyntax", "discussion_type": null, "num_comments": 0, "send_replies": true, "whitelist_status": "all_ads", "contest_mode": false, "mod_reports": [], "author_patreon_flair": false, "author_flair_text_color": null, "permalink": "/r/javascript/comments/jmwx33/javascripts_memory_management_explained/", "parent_whitelist_status": "all_ads", "stickied": false, "url": "https://felixgerschau.com/javascript-memory-management/?ck_subscriber_id=478674400", "subreddit_subscribers": 1223522, "created_utc": 1604353340.0, "num_crossposts": 0, "media": null, "is_video": false}}, {"kind": "t3", "data": {"approved_at_utc": null, "subreddit": "javascript", "selftext": "", "author_fullname": "t2_5suorbi5", "saved": false, "mod_reason_title": null, "gilded": 0, "clicked": false, "title": "Build and publish a Chrome Extension", "link_flair_richtext": [], "subreddit_name_prefixed": "r/javascript", "hidden": false, "pwls": 6, "link_flair_css_class": null, "downs": 0, "top_awarded_type": null, "hide_score": false, "name": "t3_jn6or8", "quarantine": false, "link_flair_text_color": "dark", "upvote_ratio": 0.83, "author_flair_background_color": null, "subreddit_type": "public", "ups": 4, "total_awards_received": 0, "media_embed": {}, "author_flair_template_id": null, "is_original_content": false, "user_reports": [], "secure_media": null, "is_reddit_media_domain": false, "is_meta": false, "category": null, "secure_media_embed": {}, "link_flair_text": null, "can_mod_post": false, "score": 4, "approved_by": null, "author_premium": false, "thumbnail": "", "edited": false, "author_flair_css_class": null, "author_flair_richtext": [], "gildings": {}, "content_categories": null, "is_self": false, "mod_note": null, "created": 1604420460.0, "link_flair_type": "text", "wls": 6, "removed_by_category": null, "banned_by": null, "author_flair_type": "text", "domain": "devrk.hashnode.dev", "allow_live_comments": false, "selftext_html": null, "likes": null, "suggested_sort": null, "banned_at_utc": null, "url_overridden_by_dest": "https://devrk.hashnode.dev/build-and-publish-a-chrome-extension", "view_count": null, "archived": false, "no_follow": true, "is_crosspostable": false, "pinned": false, "over_18": false, "all_awardings": [], "awarders": [], "media_only": false, "can_gild": false, "spoiler": false, "locked": false, "author_flair_text": null, "treatment_tags": [], "visited": false, "removed_by": null, "num_reports": null, "distinguished": null, "subreddit_id": "t5_2qh30", "mod_reason_by": null, "removal_reason": null, "link_flair_background_color": "", "id": "jn6or8", "is_robot_indexable": true, "report_reasons": null, "author": "geekrk", "discussion_type": null, "num_comments": 0, "send_replies": true, "whitelist_status": "all_ads", "contest_mode": false, "mod_reports": [], "author_patreon_flair": false, "author_flair_text_color": null, "permalink": "/r/javascript/comments/jn6or8/build_and_publish_a_chrome_extension/", "parent_whitelist_status": "all_ads", "stickied": false, "url": "https://devrk.hashnode.dev/build-and-publish-a-chrome-extension", "subreddit_subscribers": 1223522, "created_utc": 1604391660.0, "num_crossposts": 0, "media": null, "is_video": false}}, {"kind": "t3", "data": {"approved_at_utc": null, "subreddit": "javascript", "selftext": "", "author_fullname": "t2_atc69", "saved": false, "mod_reason_title": null, "gilded": 0, "clicked": false, "title": "Finally, a curation of 10 React security best practices", "link_flair_richtext": [], "subreddit_name_prefixed": "r/javascript", "hidden": false, "pwls": 6, "link_flair_css_class": null, "downs": 0, "top_awarded_type": null, "hide_score": false, "name": "t3_jmweez", "quarantine": false, "link_flair_text_color": "dark", "upvote_ratio": 0.86, "author_flair_background_color": null, "subreddit_type": "public", "ups": 25, "total_awards_received": 0, "media_embed": {}, "author_flair_template_id": null, "is_original_content": false, "user_reports": [], "secure_media": null, "is_reddit_media_domain": false, "is_meta": false, "category": null, "secure_media_embed": {}, "link_flair_text": null, "can_mod_post": false, "score": 25, "approved_by": null, "author_premium": false, "thumbnail": "", "edited": false, "author_flair_css_class": null, "author_flair_richtext": [], "gildings": {}, "content_categories": null, "is_self": false, "mod_note": null, "created": 1604380563.0, "link_flair_type": "text", "wls": 6, "removed_by_category": null, "banned_by": null, "author_flair_type": "text", "domain": "snyk.io", "allow_live_comments": false, "selftext_html": null, "likes": null, "suggested_sort": null, "banned_at_utc": null, "url_overridden_by_dest": "https://snyk.io/blog/10-react-security-best-practices/", "view_count": null, "archived": false, "no_follow": false, "is_crosspostable": false, "pinned": false, "over_18": false, "all_awardings": [], "awarders": [], "media_only": false, "can_gild": false, "spoiler": false, "locked": false, "author_flair_text": null, "treatment_tags": [], "visited": false, "removed_by": null, "num_reports": null, "distinguished": null, "subreddit_id": "t5_2qh30", "mod_reason_by": null, "removal_reason": null, "link_flair_background_color": "", "id": "jmweez", "is_robot_indexable": true, "report_reasons": null, "author": "lirantal", "discussion_type": null, "num_comments": 5, "send_replies": true, "whitelist_status": "all_ads", "contest_mode": false, "mod_reports": [], "author_patreon_flair": false, "author_flair_text_color": null, "permalink": "/r/javascript/comments/jmweez/finally_a_curation_of_10_react_security_best/", "parent_whitelist_status": "all_ads", "stickied": false, "url": "https://snyk.io/blog/10-react-security-best-practices/", "subreddit_subscribers": 1223522, "created_utc": 1604351763.0, "num_crossposts": 0, "media": null, "is_video": false}}, {"kind": "t3", "data": {"approved_at_utc": null, "subreddit": "javascript", "selftext": "", "author_fullname": "t2_2yd2micy", "saved": false, "mod_reason_title": null, "gilded": 0, "clicked": false, "title": "Hackathon on new Javascript based SDK", "link_flair_richtext": [], "subreddit_name_prefixed": "r/javascript", "hidden": false, "pwls": 6, "link_flair_css_class": null, "downs": 0, "top_awarded_type": null, "hide_score": false, "name": "t3_jn521a", "quarantine": false, "link_flair_text_color": "dark", "upvote_ratio": 1.0, "author_flair_background_color": null, "subreddit_type": "public", "ups": 4, "total_awards_received": 0, "media_embed": {}, "author_flair_template_id": null, "is_original_content": false, "user_reports": [], "secure_media": null, "is_reddit_media_domain": false, "is_meta": false, "category": null, "secure_media_embed": {}, "link_flair_text": null, "can_mod_post": false, "score": 4, "approved_by": null, "author_premium": false, "thumbnail": "", "edited": false, "author_flair_css_class": null, "author_flair_richtext": [], "gildings": {}, "content_categories": null, "is_self": false, "mod_note": null, "created": 1604411898.0, "link_flair_type": "text", "wls": 6, "removed_by_category": null, "banned_by": null, "author_flair_type": "text", "domain": "gitcoin.co", "allow_live_comments": false, "selftext_html": null, "likes": null, "suggested_sort": null, "banned_at_utc": null, "url_overridden_by_dest": "https://gitcoin.co/hackathon/oasis/onboard", "view_count": null, "archived": false, "no_follow": true, "is_crosspostable": false, "pinned": false, "over_18": false, "all_awardings": [], "awarders": [], "media_only": false, "can_gild": false, "spoiler": false, "locked": false, "author_flair_text": null, "treatment_tags": [], "visited": false, "removed_by": null, "num_reports": null, "distinguished": null, "subreddit_id": "t5_2qh30", "mod_reason_by": null, "removal_reason": null, "link_flair_background_color": "", "id": "jn521a", "is_robot_indexable": true, "report_reasons": null, "author": "afauvre", "discussion_type": null, "num_comments": 0, "send_replies": true, "whitelist_status": "all_ads", "contest_mode": false, "mod_reports": [], "author_patreon_flair": false, "author_flair_text_color": null, "permalink": "/r/javascript/comments/jn521a/hackathon_on_new_javascript_based_sdk/", "parent_whitelist_status": "all_ads", "stickied": false, "url": "https://gitcoin.co/hackathon/oasis/onboard", "subreddit_subscribers": 1223522, "created_utc": 1604383098.0, "num_crossposts": 0, "media": null, "is_video": false}}, {"kind": "t3", "data": {"approved_at_utc": null, "subreddit": "javascript", "selftext": "", "author_fullname": "t2_2meol7wc", "saved": false, "mod_reason_title": null, "gilded": 0, "clicked": false, "title": "A tiny GEDCOM parser", "link_flair_richtext": [], "subreddit_name_prefixed": "r/javascript", "hidden": false, "pwls": 6, "link_flair_css_class": null, "downs": 0, "top_awarded_type": null, "hide_score": true, "name": "t3_jn9t8b", "quarantine": false, "link_flair_text_color": "dark", "upvote_ratio": 1.0, "author_flair_background_color": null, "subreddit_type": "public", "ups": 1, "total_awards_received": 0, "media_embed": {}, "author_flair_template_id": null, "is_original_content": false, "user_reports": [], "secure_media": null, "is_reddit_media_domain": false, "is_meta": false, "category": null, "secure_media_embed": {}, "link_flair_text": null, "can_mod_post": false, "score": 1, "approved_by": null, "author_premium": false, "thumbnail": "", "edited": false, "author_flair_css_class": null, "author_flair_richtext": [], "gildings": {}, "content_categories": null, "is_self": false, "mod_note": null, "created": 1604437084.0, "link_flair_type": "text", "wls": 6, "removed_by_category": null, "banned_by": null, "author_flair_type": "text", "domain": "github.com", "allow_live_comments": false, "selftext_html": null, "likes": null, "suggested_sort": null, "banned_at_utc": null, "url_overridden_by_dest": "https://github.com/thoughtsunificator/gedcom-parser", "view_count": null, "archived": false, "no_follow": true, "is_crosspostable": false, "pinned": false, "over_18": false, "all_awardings": [], "awarders": [], "media_only": false, "can_gild": false, "spoiler": false, "locked": false, "author_flair_text": null, "treatment_tags": [], "visited": false, "removed_by": null, "num_reports": null, "distinguished": null, "subreddit_id": "t5_2qh30", "mod_reason_by": null, "removal_reason": null, "link_flair_background_color": "", "id": "jn9t8b", "is_robot_indexable": true, "report_reasons": null, "author": "akishimanotomodachi", "discussion_type": null, "num_comments": 0, "send_replies": true, "whitelist_status": "all_ads", "contest_mode": false, "mod_reports": [], "author_patreon_flair": false, "author_flair_text_color": null, "permalink": "/r/javascript/comments/jn9t8b/a_tiny_gedcom_parser/", "parent_whitelist_status": "all_ads", "stickied": false, "url": "https://github.com/thoughtsunificator/gedcom-parser", "subreddit_subscribers": 1223522, "created_utc": 1604408284.0, "num_crossposts": 0, "media": null, "is_video": false}}, {"kind": "t3", "data": {"approved_at_utc": null, "subreddit": "javascript", "selftext": "", "author_fullname": "t2_xeaqp", "saved": false, "mod_reason_title": null, "gilded": 0, "clicked": false, "title": "Node 15 released: Unhandled rejections are now raised as exceptions by default", "link_flair_richtext": [], "subreddit_name_prefixed": "r/javascript", "hidden": false, "pwls": 6, "link_flair_css_class": null, "downs": 0, "top_awarded_type": null, "hide_score": false, "name": "t3_jmi8jk", "quarantine": false, "link_flair_text_color": "dark", "upvote_ratio": 0.99, "author_flair_background_color": null, "subreddit_type": "public", "ups": 200, "total_awards_received": 0, "media_embed": {}, "author_flair_template_id": null, "is_original_content": false, "user_reports": [], "secure_media": null, "is_reddit_media_domain": false, "is_meta": false, "category": null, "secure_media_embed": {}, "link_flair_text": null, "can_mod_post": false, "score": 200, "approved_by": null, "author_premium": false, "thumbnail": "", "edited": false, "author_flair_css_class": null, "author_flair_richtext": [], "gildings": {}, "content_categories": null, "is_self": false, "mod_note": null, "created": 1604325699.0, "link_flair_type": "text", "wls": 6, "removed_by_category": null, "banned_by": null, "author_flair_type": "text", "domain": "nodejs.medium.com", "allow_live_comments": true, "selftext_html": null, "likes": null, "suggested_sort": null, "banned_at_utc": null, "url_overridden_by_dest": "https://nodejs.medium.com/node-js-v15-0-0-is-here-deb00750f278", "view_count": null, "archived": false, "no_follow": false, "is_crosspostable": false, "pinned": false, "over_18": false, "all_awardings": [], "awarders": [], "media_only": false, "can_gild": false, "spoiler": false, "locked": false, "author_flair_text": null, "treatment_tags": [], "visited": false, "removed_by": null, "num_reports": null, "distinguished": null, "subreddit_id": "t5_2qh30", "mod_reason_by": null, "removal_reason": null, "link_flair_background_color": "", "id": "jmi8jk", "is_robot_indexable": true, "report_reasons": null, "author": "fagnerbrack", "discussion_type": null, "num_comments": 8, "send_replies": true, "whitelist_status": "all_ads", "contest_mode": false, "mod_reports": [], "author_patreon_flair": false, "author_flair_text_color": null, "permalink": "/r/javascript/comments/jmi8jk/node_15_released_unhandled_rejections_are_now/", "parent_whitelist_status": "all_ads", "stickied": false, "url": "https://nodejs.medium.com/node-js-v15-0-0-is-here-deb00750f278", "subreddit_subscribers": 1223522, "created_utc": 1604296899.0, "num_crossposts": 0, "media": null, "is_video": false}}], "after": "t3_jmi8jk", "before": null}}